qualysconnect
