Metadata-Version: 1.0
Name: QualysConnect
Version: 0.0.8
Summary: uWaterloo QualysGuard(R) QualysConnect Package
Home-page: http://ist.uwaterloo.ca/iss/projects/qualysconnect.html
Author: Colin Bell
Author-email: colin.bell@uwaterloo.ca
License: BSD-new
Keywords: Qualys QualysGuard API helper network security
Platform: UNKNOWN
Classifier: Development Status :: 3 - Alpha
Classifier: Topic :: Utilities
Classifier: License :: OSI Approved :: BSD License
